pycrypter/__init__.py
pycrypter/_methods.py
newguy103_pycrypter-1.0.1.dist-info/METADATA
newguy103_pycrypter-1.0.1.dist-info/WHEEL
newguy103_pycrypter-1.0.1.dist-info/top_level.txt
newguy103_pycrypter-1.0.1.dist-info/RECORD
