Metadata-Version: 2.1
Name: newguy103-pycrypter
Version: 1.0.1
Summary: Simple cryptography wrapper created with threading.
Home-page: https://github.com/newguy103/pycrypter
Author: NewGuy103
Author-email: userchouenthusiast@gmail.com
Classifier: Programming Language :: Python :: 3
Requires-Dist: cryptography
